tox_current_env/__init__.py
tox_current_env/hooks.py
tox_current_env/hooks3.py
tox_current_env/hooks4.py
tox_current_env-0.0.16.dist-info/LICENSE
tox_current_env-0.0.16.dist-info/METADATA
tox_current_env-0.0.16.dist-info/WHEEL
tox_current_env-0.0.16.dist-info/entry_points.txt
tox_current_env-0.0.16.dist-info/top_level.txt
tox_current_env-0.0.16.dist-info/RECORD
