Metadata-Version: 2.2
Name: tox-current-env
Version: 0.0.16
Summary: Use current environment instead of virtualenv for tox testenvs
Home-page: https://github.com/fedora-python/tox-current-env
Author: Miro Hrončok
Author-email: miro@hroncok.cz
License: MIT
Classifier: Development Status :: 3 - Alpha
Classifier: Framework :: tox
Classifier: Intended Audience :: Developers
Classifier: License :: OSI Approved :: MIT License
Classifier: Operating System :: POSIX :: Linux
Classifier: Programming Language :: Python :: 3 :: Only
Classifier: Programming Language :: Python :: 3.6
Classifier: Programming Language :: Python :: 3.7
Classifier: Programming Language :: Python :: 3.8
Classifier: Programming Language :: Python :: 3.9
Classifier: Programming Language :: Python :: 3.10
Classifier: Programming Language :: Python :: 3.11
Classifier: Programming Language :: Python :: Implementation :: CPython
Classifier: Topic :: Software Development :: Testing
Requires-Python: >=3.6
License-File: LICENSE
Requires-Dist: tox>=3.28
Requires-Dist: importlib_metadata; python_version < "3.8"
Provides-Extra: tests
Requires-Dist: pytest; extra == "tests"
Requires-Dist: pytest-xdist; extra == "tests"
Requires-Dist: packaging; extra == "tests"
Dynamic: author
Dynamic: author-email
Dynamic: classifier
Dynamic: description
Dynamic: home-page
Dynamic: license
Dynamic: provides-extra
Dynamic: requires-dist
Dynamic: requires-python
Dynamic: summary
